connection_uri/__init__.py
connection_uri/__init__.pyc
connection_uri/uri.py
connection_uri/uri.pyc
connection_uri/tests/__init__.py
connection_uri/tests/__main__.py
connection_uri/tests/helper.py
connection_uri/tests/test_uri.py
connection_uri-0.1.1.dist-info/METADATA
connection_uri-0.1.1.dist-info/WHEEL
connection_uri-0.1.1.dist-info/top_level.txt
connection_uri-0.1.1.dist-info/zip-safe
connection_uri-0.1.1.dist-info/RECORD
